devind_helpers/__init__.py
devind_helpers/exceptions.py
devind_helpers/files/__init__.py
devind_helpers/files/cleaner.py
devind_helpers/files/sign_synchronizer.py
devind_helpers/files/utils.py
devind_helpers/generators/__init__.py
devind_helpers/generators/document_generator.py
devind_helpers/import_from_file/__init__.py
devind_helpers/import_from_file/base_reader.py
devind_helpers/import_from_file/csv_reader.py
devind_helpers/import_from_file/excel_reader.py
devind_helpers/import_from_file/exceptions.py
devind_helpers/import_from_file/import_from_file.py
devind_helpers/import_from_file/json_reader.py
devind_helpers/import_from_file/ratio.py
devind_helpers/orm_utils.py
devind_helpers/relations.py
devind_helpers/request.py
devind_helpers/schema/__init__.py
devind_helpers/schema/types.py
devind_helpers/unpack_zip.py
devind_helpers/utils.py
devind_helpers-1.0.1.dist-info/LICENSE
devind_helpers-1.0.1.dist-info/WHEEL
devind_helpers-1.0.1.dist-info/METADATA
devind_helpers-1.0.1.dist-info/RECORD
